portinvartija/__init__.py
portinvartija/__main__.py
portinvartija/cli.py
portinvartija/portinvartija.py
portinvartija-2023.10.29.dist-info/LICENSE
portinvartija-2023.10.29.dist-info/METADATA
portinvartija-2023.10.29.dist-info/WHEEL
portinvartija-2023.10.29.dist-info/entry_points.txt
portinvartija-2023.10.29.dist-info/top_level.txt
portinvartija-2023.10.29.dist-info/RECORD
