Metadata-Version: 2.1
Name: portinvartija
Version: 2023.10.29
Summary: Python implementation of interface operations for data driven topics.
Author-email: Stefan Hagen <stefan@hagen.link>
Maintainer-email: Stefan Hagen <stefan@hagen.link>
Project-URL: Homepage, https://git.sr.ht/~sthagen/portinvartija
Project-URL: Bug-Tracker, https://todo.sr.ht/~sthagen/portinvartija
Project-URL: Documentation, https://codes.dilettant.life/docs/portinvartija
Project-URL: Source-Code, https://git.sr.ht/~sthagen/portinvartija
Project-URL: Test-Coverage, https://codes.dilettant.life/coverage/portinvartija
Keywords: developer-tools,verification
Classifier: Development Status :: 3 - Alpha
Classifier: Intended Audience :: Developers
Classifier: License :: OSI Approved :: MIT License
Classifier: Programming Language :: Python :: 3.10
Classifier: Programming Language :: Python :: 3.11
Classifier: Programming Language :: Python :: 3.12
Classifier: Programming Language :: Python :: 3.9
Requires-Python: >=3.9
License-File: LICENSE
Requires-Dist: PyYAML >=6.0.1
Requires-Dist: first >=2.0.2
Requires-Dist: jmespath >=1.0.1
Requires-Dist: jsonschema >=4.19.1
Requires-Dist: kdl-py >=1.1.2
Requires-Dist: lxml >=4.9.3
Requires-Dist: msgspec >=0.18.4
Requires-Dist: referencing >=0.30.2
Requires-Dist: toml >=0.10.2
Requires-Dist: typer >=0.9.0
Requires-Dist: xmlschema >=2.5.0
Provides-Extra: dev
Requires-Dist: black ; extra == 'dev'
Requires-Dist: coverage ; extra == 'dev'
Requires-Dist: hypothesis ; extra == 'dev'
Requires-Dist: mypy ; extra == 'dev'
Requires-Dist: pytest ; extra == 'dev'
Requires-Dist: pytest-cov ; extra == 'dev'
Requires-Dist: pytest-flake8 ; extra == 'dev'
Requires-Dist: ruff ; extra == 'dev'
